apisports_football/__init__.py
apisports_football/apiclient.py
apisports_football/exceptions.py
apisports_football/utils.py
apisports_football/wrapper.py
apisports_football/Endpoints/__init__.py
apisports_football/Endpoints/coachs.py
apisports_football/Endpoints/countries.py
apisports_football/Endpoints/fixtures.py
apisports_football/Endpoints/injuries.py
apisports_football/Endpoints/leagues.py
apisports_football/Endpoints/odds.py
apisports_football/Endpoints/players.py
apisports_football/Endpoints/predictions.py
apisports_football/Endpoints/sidelined.py
apisports_football/Endpoints/standings.py
apisports_football/Endpoints/teams.py
apisports_football/Endpoints/timezone.py
apisports_football/Endpoints/transfers.py
apisports_football/Endpoints/trophies.py
apisports_football/Endpoints/venues.py
apisports_football/Models/BaseModel.py
apisports_football/Models/__init__.py
apisports_football/Models/Coachs/Coachs.py
apisports_football/Models/Coachs/__init__.py
apisports_football/Models/Countries/Countries.py
apisports_football/Models/Countries/__init__.py
apisports_football/Models/Fixtures/Events.py
apisports_football/Models/Fixtures/Fixtures.py
apisports_football/Models/Fixtures/Lineups.py
apisports_football/Models/Fixtures/Players.py
apisports_football/Models/Fixtures/Rounds.py
apisports_football/Models/Fixtures/Statistics.py
apisports_football/Models/Fixtures/__init__.py
apisports_football/Models/Injuries/Injuries.py
apisports_football/Models/Injuries/__init__.py
apisports_football/Models/Leagues/Leagues.py
apisports_football/Models/Leagues/Seasons.py
apisports_football/Models/Leagues/__init__.py
apisports_football/Models/Odds/Bookmakers.py
apisports_football/Models/Odds/Live.py
apisports_football/Models/Odds/LiveBets.py
apisports_football/Models/Odds/Mapping.py
apisports_football/Models/Odds/Odds.py
apisports_football/Models/Odds/__init__.py
apisports_football/Models/Players/Players.py
apisports_football/Models/Players/Profiles.py
apisports_football-1.0.4.1.dist-info/LICENSE
apisports_football-1.0.4.1.dist-info/METADATA
apisports_football-1.0.4.1.dist-info/WHEEL
apisports_football-1.0.4.1.dist-info/top_level.txt
apisports_football-1.0.4.1.dist-info/RECORD
