Metadata-Version: 2.1
Name: apisports_football
Version: 1.0.4.1
Summary: Asynchronous wrapper for football API from API-SPORTS
Author-email: h3ave <noth3ave@yandex.ru>
License: MIT License
Project-URL: Changelog, https://github.com/h3ave/apisports_football/blob/main/CHANGELOG.md
Project-URL: Repository, https://github.com/h3ave/apisports_football
Keywords: football,api,wrapper,apisports
Classifier: Programming Language :: Python :: 3.7
Classifier: Programming Language :: Python :: 3.8
Classifier: Programming Language :: Python :: 3.9
Classifier: Programming Language :: Python :: 3.10
Classifier: Programming Language :: Python :: 3.11
Classifier: Programming Language :: Python :: 3.12
Classifier: Programming Language :: Python :: 3.13
Classifier: License :: OSI Approved :: MIT License
Classifier: Operating System :: OS Independent
Requires-Python: >=3.7
License-File: LICENSE
Requires-Dist: aiohttp >=3.8.6
Requires-Dist: pydantic >=2.5.3
Requires-Dist: typing-extensions >=4.7.1
